spmo_client/__init__.py
spmo_client/api_client.py
spmo_client/configuration.py
spmo_client/rest.py
spmo_client/api/__init__.py
spmo_client/api/organizations_api.py
spmo_client/api/person_stakeholder_api.py
spmo_client/api/person_stakeholders_api.py
spmo_client/api/project_processes_api.py
spmo_client/api/software_project_api.py
spmo_client/api/software_projects_api.py
spmo_client/api/stakeholders_api.py
spmo_client/api/tracked_activities_api.py
spmo_client/api/tracked_project_processe_api.py
spmo_client/api/tracked_project_processes_api.py
spmo_client/api/tracked_stakeholder_participation_api.py
spmo_client/models/__init__.py
spmo_client/models/organization_.py
spmo_client/models/person_stakeholder_.py
spmo_client/models/project_process_.py
spmo_client/models/software_project_.py
spmo_client/models/stakeholder_.py
spmo_client/models/tracked_activity_.py
spmo_client/models/tracked_project_process_.py
spmo_client/models/tracked_stakeholder_participation_.py
test/__init__.py
test/test_organization_.py
test/test_organizations_api.py
test/test_person_stakeholder_.py
test/test_person_stakeholder_api.py
test/test_person_stakeholders_api.py
test/test_project_process_.py
test/test_project_processes_api.py
test/test_software_project_.py
test/test_software_project_api.py
test/test_software_projects_api.py
test/test_stakeholder_.py
test/test_stakeholders_api.py
test/test_tracked_activities_api.py
test/test_tracked_activity_.py
test/test_tracked_project_process_.py
test/test_tracked_project_processe_api.py
test/test_tracked_project_processes_api.py
test/test_tracked_stakeholder_participation_.py
test/test_tracked_stakeholder_participation_api.py
spmo_client-1.0.2.dist-info/METADATA
spmo_client-1.0.2.dist-info/WHEEL
spmo_client-1.0.2.dist-info/top_level.txt
spmo_client-1.0.2.dist-info/RECORD
