Metadata-Version: 2.1
Name: spmo-client
Version: 1.0.2
Summary: SPMO Service
Home-page: UNKNOWN
Author: UNKNOWN
Author-email: UNKNOWN
License: UNKNOWN
Keywords: Swagger,SPMO Service
Platform: UNKNOWN
Requires-Dist: certifi (>=2017.4.17)
Requires-Dist: python-dateutil (>=2.1)
Requires-Dist: six (>=1.10)
Requires-Dist: urllib3 (>=1.23)
